[
    {
        "kind": "Listing",
        "data": {
            "after": null,
            "dist": 1,
            "modhash": "cnfgw4ugmc6bb75362bc0967b9a7c422f366c35de7699bef2d",
            "geo_filter": "",
            "children": [
                {
                    "kind": "t3",
                    "data": {
                        "approved_at_utc": null,
                        "subreddit": "redditdev",
                        "selftext": "I'm looking at the reddit API and I can't seem to figure out how to get more comments from a post after the initial 50. The text below is from the reddit API:\n\n\n*Fetching more*\n\n*If you're fetching comments from a thread with more comments than the API will return in a single response, the last comment will look like this:*\n\n*{'data': {'id': 'abc1010', 'name': 't1_abc1010'}, 'kind': 'more'}*\n\n*To get these comments, you can fetch the url http://reddit.com/comments/FULLNAME/abc1010.json, where FULLNAME is the FULLNAME of the story.*\n\n\nTo use as an example for my problem, when I get the json from:\nhttp://www.reddit.com/r/funny/comments/o0pk5/monopoly_is_an_old_game/.json\n\nI am able to see the first 50 parent comments. At the end of the JSON Array for these comments, there is another item labeled \"more\" which has an id of \"c3dibkp\". \n\nSo according to the API, I should be able to fetch more comments by accessing:\n\nhttp://reddit.com/comments/FULLNAME/c3dibkp.json\n\nI'm guessing that FULLNAME should be equal to the id of the original story, which is \"o0pk5\".\n\nHowever I cannot seem to get the correct results using:\nhttp://reddit.com/comments/o0pk5/c3dibkp.json\n\nWhat am I doing wrong?\n",
                        "user_reports": [],
                        "saved": false,
                        "mod_reason_title": null,
                        "gilded": 0,
                        "clicked": false,
                        "title": "How do I get more comments in JSON format?",
                        "link_flair_richtext": [],
                        "subreddit_name_prefixed": "r/redditdev",
                        "hidden": false,
                        "pwls": 6,
                        "link_flair_css_class": null,
                        "downs": 0,
                        "top_awarded_type": null,
                        "parent_whitelist_status": "all_ads",
                        "hide_score": false,
                        "name": "t3_o1w7b",
                        "quarantine": false,
                        "link_flair_text_color": "dark",
                        "upvote_ratio": 0.9,
                        "author_flair_background_color": null,
                        "subreddit_type": "public",
                        "ups": 13,
                        "total_awards_received": 0,
                        "media_embed": {},
                        "author_flair_template_id": null,
                        "is_original_content": false,
                        "author_fullname": "t2_3r45h",
                        "secure_media": null,
                        "is_reddit_media_domain": false,
                        "is_meta": false,
                        "category": null,
                        "secure_media_embed": {},
                        "link_flair_text": null,
                        "can_mod_post": false,
                        "score": 13,
                        "approved_by": null,
                        "is_created_from_ads_ui": false,
                        "author_premium": false,
                        "thumbnail": "",
                        "edited": false,
                        "author_flair_css_class": null,
                        "author_flair_richtext": [],
                        "gildings": {},
                        "content_categories": null,
                        "is_self": true,
                        "mod_note": null,
                        "created": 1325642369.0,
                        "link_flair_type": "text",
                        "wls": 6,
                        "removed_by_category": null,
                        "banned_by": null,
                        "author_flair_type": "text",
                        "domain": "self.redditdev",
                        "allow_live_comments": true,
                        "selftext_html": "&lt;!-- SC_OFF --&gt;&lt;div class=\"md\"&gt;&lt;p&gt;I&amp;#39;m looking at the reddit API and I can&amp;#39;t seem to figure out how to get more comments from a post after the initial 50. The text below is from the reddit API:&lt;/p&gt;\n\n&lt;p&gt;&lt;em&gt;Fetching more&lt;/em&gt;&lt;/p&gt;\n\n&lt;p&gt;&lt;em&gt;If you&amp;#39;re fetching comments from a thread with more comments than the API will return in a single response, the last comment will look like this:&lt;/em&gt;&lt;/p&gt;\n\n&lt;p&gt;&lt;em&gt;{&amp;#39;data&amp;#39;: {&amp;#39;id&amp;#39;: &amp;#39;abc1010&amp;#39;, &amp;#39;name&amp;#39;: &amp;#39;t1_abc1010&amp;#39;}, &amp;#39;kind&amp;#39;: &amp;#39;more&amp;#39;}&lt;/em&gt;&lt;/p&gt;\n\n&lt;p&gt;&lt;em&gt;To get these comments, you can fetch the url &lt;a href=\"http://reddit.com/comments/FULLNAME/abc1010.json\"&gt;http://reddit.com/comments/FULLNAME/abc1010.json&lt;/a&gt;, where FULLNAME is the FULLNAME of the story.&lt;/em&gt;&lt;/p&gt;\n\n&lt;p&gt;To use as an example for my problem, when I get the json from:\n&lt;a href=\"http://www.reddit.com/r/funny/comments/o0pk5/monopoly_is_an_old_game/.json\"&gt;http://www.reddit.com/r/funny/comments/o0pk5/monopoly_is_an_old_game/.json&lt;/a&gt;&lt;/p&gt;\n\n&lt;p&gt;I am able to see the first 50 parent comments. At the end of the JSON Array for these comments, there is another item labeled &amp;quot;more&amp;quot; which has an id of &amp;quot;c3dibkp&amp;quot;. &lt;/p&gt;\n\n&lt;p&gt;So according to the API, I should be able to fetch more comments by accessing:&lt;/p&gt;\n\n&lt;p&gt;&lt;a href=\"http://reddit.com/comments/FULLNAME/c3dibkp.json\"&gt;http://reddit.com/comments/FULLNAME/c3dibkp.json&lt;/a&gt;&lt;/p&gt;\n\n&lt;p&gt;I&amp;#39;m guessing that FULLNAME should be equal to the id of the original story, which is &amp;quot;o0pk5&amp;quot;.&lt;/p&gt;\n\n&lt;p&gt;However I cannot seem to get the correct results using:\n&lt;a href=\"http://reddit.com/comments/o0pk5/c3dibkp.json\"&gt;http://reddit.com/comments/o0pk5/c3dibkp.json&lt;/a&gt;&lt;/p&gt;\n\n&lt;p&gt;What am I doing wrong?&lt;/p&gt;\n&lt;/div&gt;&lt;!-- SC_ON --&gt;",
                        "likes": null,
                        "suggested_sort": null,
                        "banned_at_utc": null,
                        "view_count": null,
                        "archived": false,
                        "no_follow": true,
                        "is_crosspostable": true,
                        "pinned": false,
                        "over_18": false,
                        "all_awardings": [],
                        "awarders": [],
                        "media_only": false,
                        "can_gild": true,
                        "spoiler": false,
                        "locked": false,
                        "author_flair_text": null,
                        "treatment_tags": [],
                        "visited": false,
                        "removed_by": null,
                        "num_reports": null,
                        "distinguished": null,
                        "subreddit_id": "t5_2qizd",
                        "author_is_blocked": false,
                        "mod_reason_by": null,
                        "removal_reason": null,
                        "link_flair_background_color": "",
                        "id": "o1w7b",
                        "is_robot_indexable": true,
                        "num_duplicates": 0,
                        "report_reasons": null,
                        "author": "hyperpowerr",
                        "discussion_type": null,
                        "num_comments": 10,
                        "send_replies": true,
                        "media": null,
                        "contest_mode": false,
                        "author_patreon_flair": false,
                        "author_flair_text_color": null,
                        "permalink": "/r/redditdev/comments/o1w7b/how_do_i_get_more_comments_in_json_format/",
                        "whitelist_status": "all_ads",
                        "stickied": false,
                        "url": "https://www.reddit.com/r/redditdev/comments/o1w7b/how_do_i_get_more_comments_in_json_format/",
                        "subreddit_subscribers": 71837,
                        "created_utc": 1325642369.0,
                        "num_crossposts": 0,
                        "mod_reports": [],
                        "is_video": false
                    }
                }
            ],
            "before": null
        }
    },
    {
        "kind": "Listing",
        "data": {
            "after": null,
            "dist": null,
            "modhash": "cnfgw4ugmc6bb75362bc0967b9a7c422f366c35de7699bef2d",
            "geo_filter": "",
            "children": [
                {
                    "kind": "t1",
                    "data": {
                        "subreddit_id": "t5_2qizd",
                        "approved_at_utc": null,
                        "author_is_blocked": false,
                        "comment_type": null,
                        "awarders": [],
                        "mod_reason_by": null,
                        "banned_by": null,
                        "author_flair_type": "text",
                        "total_awards_received": 0,
                        "subreddit": "redditdev",
                        "author_flair_template_id": null,
                        "likes": null,
                        "replies": {
                            "kind": "Listing",
                            "data": {
                                "after": null,
                                "dist": null,
                                "modhash": "cnfgw4ugmc6bb75362bc0967b9a7c422f366c35de7699bef2d",
                                "geo_filter": "",
                                "children": [
                                    {
                                        "kind": "t1",
                                        "data": {
                                            "total_awards_received": 0,
                                            "approved_at_utc": null,
                                            "author_is_blocked": false,
                                            "comment_type": null,
                                            "awarders": [],
                                            "mod_reason_by": null,
                                            "banned_by": null,
                                            "ups": 3,
                                            "removal_reason": null,
                                            "link_id": "t3_o1w7b",
                                            "author_flair_template_id": null,
                                            "likes": null,
                                            "replies": {
                                                "kind": "Listing",
                                                "data": {
                                                    "after": null,
                                                    "dist": null,
                                                    "modhash": "cnfgw4ugmc6bb75362bc0967b9a7c422f366c35de7699bef2d",
                                                    "geo_filter": "",
                                                    "children": [
                                                        {
                                                            "kind": "t1",
                                                            "data": {
                                                                "subreddit_id": "t5_2qizd",
                                                                "approved_at_utc": null,
                                                                "author_is_blocked": false,
                                                                "comment_type": null,
                                                                "awarders": [],
                                                                "mod_reason_by": null,
                                                                "banned_by": null,
                                                                "author_flair_type": "text",
                                                                "total_awards_received": 0,
                                                                "subreddit": "redditdev",
                                                                "author_flair_template_id": null,
                                                                "likes": null,
                                                                "replies": "",
                                                                "user_reports": [],
                                                                "saved": false,
                                                                "id": "c3dq73g",
                                                                "banned_at_utc": null,
                                                                "mod_reason_title": null,
                                                                "gilded": 0,
                                                                "archived": false,
                                                                "collapsed_reason_code": null,
                                                                "no_follow": true,
                                                                "author": "bboe",
                                                                "can_mod_post": false,
                                                                "send_replies": true,
                                                                "parent_id": "t1_c3dq1xo",
                                                                "score": 2,
                                                                "author_fullname": "t2_3pz6e",
                                                                "removal_reason": null,
                                                                "approved_by": null,
                                                                "mod_note": null,
                                                                "all_awardings": [],
                                                                "body": "&gt; How am I supposed to use these python functions if I am developing my Android app in Java?\n\nYou aren't supposed to. They are just for reference to see what parameters I pass.\n\n&gt; Are you saying that I have to actually make a request for each one to build the comment tree?\n\nAs of now, that's correct.",
                                                                "edited": false,
                                                                "top_awarded_type": null,
                                                                "downs": 0,
                                                                "author_flair_css_class": "",
                                                                "name": "t1_c3dq73g",
                                                                "is_submitter": false,
                                                                "collapsed": false,
                                                                "author_flair_richtext": [],
                                                                "author_patreon_flair": false,
                                                                "body_html": "&lt;div class=\"md\"&gt;&lt;blockquote&gt;\n&lt;p&gt;How am I supposed to use these python functions if I am developing my Android app in Java?&lt;/p&gt;\n&lt;/blockquote&gt;\n\n&lt;p&gt;You aren&amp;#39;t supposed to. They are just for reference to see what parameters I pass.&lt;/p&gt;\n\n&lt;blockquote&gt;\n&lt;p&gt;Are you saying that I have to actually make a request for each one to build the comment tree?&lt;/p&gt;\n&lt;/blockquote&gt;\n\n&lt;p&gt;As of now, that&amp;#39;s correct.&lt;/p&gt;\n&lt;/div&gt;",
                                                                "gildings": {},
                                                                "collapsed_reason": null,
                                                                "distinguished": null,
                                                                "associated_award": null,
                                                                "stickied": false,
                                                                "author_premium": false,
                                                                "can_gild": true,
                                                                "link_id": "t3_o1w7b",
                                                                "unrepliable_reason": null,
                                                                "author_flair_text_color": "dark",
                                                                "score_hidden": false,
                                                                "permalink": "/r/redditdev/comments/o1w7b/how_do_i_get_more_comments_in_json_format/c3dq73g/",
                                                                "subreddit_type": "public",
                                                                "locked": false,
                                                                "report_reasons": null,
                                                                "created": 1325649386.0,
                                                                "author_flair_text": "PRAW Author",
                                                                "treatment_tags": [],
                                                                "created_utc": 1325649386.0,
                                                                "subreddit_name_prefixed": "r/redditdev",
                                                                "controversiality": 0,
                                                                "depth": 2,
                                                                "author_flair_background_color": "",
                                                                "collapsed_because_crowd_control": null,
                                                                "mod_reports": [],
                                                                "num_reports": null,
                                                                "ups": 2
                                                            }
                                                        }
                                                    ],
                                                    "before": null
                                                }
                                            },
                                            "user_reports": [],
                                            "saved": false,
                                            "id": "c3dq1xo",
                                            "banned_at_utc": null,
                                            "mod_reason_title": null,
                                            "gilded": 0,
                                            "archived": false,
                                            "collapsed_reason_code": null,
                                            "no_follow": true,
                                            "author": "[deleted]",
                                            "can_mod_post": false,
                                            "send_replies": true,
                                            "parent_id": "t1_c3dpt9i",
                                            "score": 3,
                                            "approved_by": null,
                                            "report_reasons": null,
                                            "all_awardings": [],
                                            "subreddit_id": "t5_2qizd",
                                            "body": "[deleted]",
                                            "edited": false,
                                            "author_flair_css_class": null,
                                            "collapsed": false,
                                            "downs": 0,
                                            "is_submitter": false,
                                            "body_html": "&lt;div class=\"md\"&gt;&lt;p&gt;[deleted]&lt;/p&gt;\n&lt;/div&gt;",
                                            "gildings": {},
                                            "collapsed_reason": null,
                                            "associated_award": null,
                                            "stickied": false,
                                            "subreddit_type": "public",
                                            "can_gild": true,
                                            "top_awarded_type": null,
                                            "unrepliable_reason": null,
                                            "author_flair_text_color": "dark",
                                            "score_hidden": false,
                                            "permalink": "/r/redditdev/comments/o1w7b/how_do_i_get_more_comments_in_json_format/c3dq1xo/",
                                            "num_reports": null,
                                            "locked": false,
                                            "name": "t1_c3dq1xo",
                                            "created": 1325648347.0,
                                            "subreddit": "redditdev",
                                            "author_flair_text": null,
                                            "treatment_tags": [],
                                            "created_utc": 1325648347.0,
                                            "subreddit_name_prefixed": "r/redditdev",
                                            "controversiality": 0,
                                            "depth": 1,
                                            "author_flair_background_color": "",
                                            "collapsed_because_crowd_control": null,
                                            "mod_reports": [],
                                            "mod_note": null,
                                            "distinguished": null
                                        }
                                    },
                                    {
                                        "kind": "t1",
                                        "data": {
                                            "subreddit_id": "t5_2qizd",
                                            "approved_at_utc": null,
                                            "author_is_blocked": false,
                                            "comment_type": null,
                                            "awarders": [],
                                            "mod_reason_by": null,
                                            "banned_by": null,
                                            "author_flair_type": "text",
                                            "total_awards_received": 0,
                                            "subreddit": "redditdev",
                                            "author_flair_template_id": null,
                                            "likes": null,
                                            "replies": {
                                                "kind": "Listing",
                                                "data": {
                                                    "after": null,
                                                    "dist": null,
                                                    "modhash": "cnfgw4ugmc6bb75362bc0967b9a7c422f366c35de7699bef2d",
                                                    "geo_filter": "",
                                                    "children": [
                                                        {
                                                            "kind": "t1",
                                                            "data": {
                                                                "subreddit_id": "t5_2qizd",
                                                                "approved_at_utc": null,
                                                                "author_is_blocked": false,
                                                                "comment_type": null,
                                                                "awarders": [],
                                                                "mod_reason_by": null,
                                                                "banned_by": null,
                                                                "author_flair_type": "text",
                                                                "total_awards_received": 0,
                                                                "subreddit": "redditdev",
                                                                "author_flair_template_id": null,
                                                                "likes": null,
                                                                "replies": "",
                                                                "user_reports": [],
                                                                "saved": false,
                                                                "id": "c3dry82",
                                                                "banned_at_utc": null,
                                                                "mod_reason_title": null,
                                                                "gilded": 0,
                                                                "archived": false,
                                                                "collapsed_reason_code": null,
                                                                "no_follow": true,
                                                                "author": "bboe",
                                                                "can_mod_post": false,
                                                                "send_replies": true,
                                                                "parent_id": "t1_c3drgxh",
                                                                "score": 2,
                                                                "author_fullname": "t2_3pz6e",
                                                                "removal_reason": null,
                                                                "approved_by": null,
                                                                "mod_note": null,
                                                                "all_awardings": [],
                                                                "body": "It would be nice to batch request all the comments. However, the problem is the server has to build all the comment trees as well which is currently the problem. A fix is definitely required to more efficiently solve the problem.\n\nI had a discussion on IRC with the admins about this issue. I discussed possibly just iterating over comments by date, and relying on the client to build the tree thus allowing you to simply fetch up to 1000 comments at a time, with a `next` parameter. That seems like the way to go.",
                                                                "edited": 1325666122.0,
                                                                "top_awarded_type": null,
                                                                "downs": 0,
                                                                "author_flair_css_class": "",
                                                                "name": "t1_c3dry82",
                                                                "is_submitter": false,
                                                                "collapsed": false,
                                                                "author_flair_richtext": [],
                                                                "author_patreon_flair": false,
                                                                "body_html": "&lt;div class=\"md\"&gt;&lt;p&gt;It would be nice to batch request all the comments. However, the problem is the server has to build all the comment trees as well which is currently the problem. A fix is definitely required to more efficiently solve the problem.&lt;/p&gt;\n\n&lt;p&gt;I had a discussion on IRC with the admins about this issue. I discussed possibly just iterating over comments by date, and relying on the client to build the tree thus allowing you to simply fetch up to 1000 comments at a time, with a &lt;code&gt;next&lt;/code&gt; parameter. That seems like the way to go.&lt;/p&gt;\n&lt;/div&gt;",
                                                                "gildings": {},
                                                                "collapsed_reason": null,
                                                                "distinguished": null,
                                                                "associated_award": null,
                                                                "stickied": false,
                                                                "author_premium": false,
                                                                "can_gild": true,
                                                                "link_id": "t3_o1w7b",
                                                                "unrepliable_reason": null,
                                                                "author_flair_text_color": "dark",
                                                                "score_hidden": false,
                                                                "permalink": "/r/redditdev/comments/o1w7b/how_do_i_get_more_comments_in_json_format/c3dry82/",
                                                                "subreddit_type": "public",
                                                                "locked": false,
                                                                "report_reasons": null,
                                                                "created": 1325662522.0,
                                                                "author_flair_text": "PRAW Author",
                                                                "treatment_tags": [],
                                                                "created_utc": 1325662522.0,
                                                                "subreddit_name_prefixed": "r/redditdev",
                                                                "controversiality": 0,
                                                                "depth": 2,
                                                                "author_flair_background_color": "",
                                                                "collapsed_because_crowd_control": null,
                                                                "mod_reports": [],
                                                                "num_reports": null,
                                                                "ups": 2
                                                            }
                                                        }
                                                    ],
                                                    "before": null
                                                }
                                            },
                                            "user_reports": [],
                                            "saved": false,
                                            "id": "c3drgxh",
                                            "banned_at_utc": null,
                                            "mod_reason_title": null,
                                            "gilded": 0,
                                            "archived": false,
                                            "collapsed_reason_code": null,
                                            "no_follow": true,
                                            "author": "fullouterjoin",
                                            "can_mod_post": false,
                                            "created_utc": 1325658511.0,
                                            "send_replies": true,
                                            "parent_id": "t1_c3dpt9i",
                                            "score": 2,
                                            "author_fullname": "t2_406sj",
                                            "removal_reason": null,
                                            "approved_by": null,
                                            "mod_note": null,
                                            "all_awardings": [],
                                            "body": "wow, that is a lot of work. Do you think it would be easier to send a patch to cleanup how downloading more comments works? Seems a little wonky to me.",
                                            "edited": false,
                                            "top_awarded_type": null,
                                            "author_flair_css_class": null,
                                            "name": "t1_c3drgxh",
                                            "is_submitter": false,
                                            "downs": 0,
                                            "author_flair_richtext": [],
                                            "author_patreon_flair": false,
                                            "body_html": "&lt;div class=\"md\"&gt;&lt;p&gt;wow, that is a lot of work. Do you think it would be easier to send a patch to cleanup how downloading more comments works? Seems a little wonky to me.&lt;/p&gt;\n&lt;/div&gt;",
                                            "gildings": {},
                                            "collapsed_reason": null,
                                            "distinguished": null,
                                            "associated_award": null,
                                            "stickied": false,
                                            "author_premium": false,
                                            "can_gild": true,
                                            "link_id": "t3_o1w7b",
                                            "unrepliable_reason": null,
                                            "author_flair_text_color": null,
                                            "score_hidden": false,
                                            "permalink": "/r/redditdev/comments/o1w7b/how_do_i_get_more_comments_in_json_format/c3drgxh/",
                                            "subreddit_type": "public",
                                            "locked": false,
                                            "report_reasons": null,
                                            "created": 1325658511.0,
                                            "author_flair_text": null,
                                            "treatment_tags": [],
                                            "collapsed": false,
                                            "subreddit_name_prefixed": "r/redditdev",
                                            "controversiality": 0,
                                            "depth": 1,
                                            "author_flair_background_color": null,
                                            "collapsed_because_crowd_control": null,
                                            "mod_reports": [],
                                            "num_reports": null,
                                            "ups": 2
                                        }
                                    }
                                ],
                                "before": null
                            }
                        },
                        "user_reports": [],
                        "saved": false,
                        "id": "c3dpt9i",
                        "banned_at_utc": null,
                        "mod_reason_title": null,
                        "gilded": 0,
                        "archived": false,
                        "collapsed_reason_code": null,
                        "no_follow": false,
                        "author": "bboe",
                        "can_mod_post": false,
                        "created_utc": 1325646819.0,
                        "send_replies": true,
                        "parent_id": "t3_o1w7b",
                        "score": 4,
                        "author_fullname": "t2_3pz6e",
                        "approved_by": null,
                        "mod_note": null,
                        "all_awardings": [],
                        "collapsed": false,
                        "body": "Hi, maintainer of the [reddit api wrapper](https://github.com/mellort/reddit_api) here. I also happened to [add the fix](https://github.com/reddit/reddit/commit/60f704ef89fe513dff2608380545786c74e95428) that makes the \"more\" object list items now. The API documentation explaining how to fetch additional comments is incorrect.\n\nBasically, for each of those `more` items you need to make a __POST__ request to `api/morechildren` with the parameters `children`, `link_id`, `r` and `api_type`.\n\n`children` should be a comma separated list of IDs directly corresponding to the IDs of the `children` field in the `more` object. It would appear that in your example, the each of the `more` objects' children only have one id which also happen to match the `more` object id.\n\n`link_id` should be the ID of the submission. In your case, `t3_o0pk5`.\n\n`r` is the name of the subreddit, and is only needed if you don't include the subreddit in the URL (see my comments on [this post](http://www.reddit.com/r/redditdev/comments/nvlmb/does_anyone_have_an_example_of_an_apiflairlist/) for the explanation).\n\n`api_type` is only needed if you want to receive json results. Appending `.json` to the URL may accomplish the same thing, though I've found with `POST` requests, that typically isn't the case as often you'll get back _jquery_ results.\n\nIf you can follow python check out my code here:\nhttps://github.com/mellort/reddit_api/blob/master/reddit/objects.py#L254\n\n---\n\nEdit: I forgot to mention, that the `children` IDs may not always actually be children of the location where the `more` object appears. Thus you have to manually reconstruct the comment tree.\n\nAlso, knowing that I had to manually reconstruct the tree, I figured I could just batch request all the `more` IDs. Unfortunately that doesn't work, as it'll only return a partial result. You have to make one request for each `more` object, which makes obtaining all the comments for a heavily-commented submission require numerous requests.",
                        "edited": 1325650419.0,
                        "top_awarded_type": null,
                        "author_flair_css_class": "",
                        "name": "t1_c3dpt9i",
                        "is_submitter": false,
                        "downs": 0,
                        "author_flair_richtext": [],
                        "author_patreon_flair": false,
                        "body_html": "&lt;div class=\"md\"&gt;&lt;p&gt;Hi, maintainer of the &lt;a href=\"https://github.com/mellort/reddit_api\"&gt;reddit api wrapper&lt;/a&gt; here. I also happened to &lt;a href=\"https://github.com/reddit/reddit/commit/60f704ef89fe513dff2608380545786c74e95428\"&gt;add the fix&lt;/a&gt; that makes the &amp;quot;more&amp;quot; object list items now. The API documentation explaining how to fetch additional comments is incorrect.&lt;/p&gt;\n\n&lt;p&gt;Basically, for each of those &lt;code&gt;more&lt;/code&gt; items you need to make a &lt;strong&gt;POST&lt;/strong&gt; request to &lt;code&gt;api/morechildren&lt;/code&gt; with the parameters &lt;code&gt;children&lt;/code&gt;, &lt;code&gt;link_id&lt;/code&gt;, &lt;code&gt;r&lt;/code&gt; and &lt;code&gt;api_type&lt;/code&gt;.&lt;/p&gt;\n\n&lt;p&gt;&lt;code&gt;children&lt;/code&gt; should be a comma separated list of IDs directly corresponding to the IDs of the &lt;code&gt;children&lt;/code&gt; field in the &lt;code&gt;more&lt;/code&gt; object. It would appear that in your example, the each of the &lt;code&gt;more&lt;/code&gt; objects&amp;#39; children only have one id which also happen to match the &lt;code&gt;more&lt;/code&gt; object id.&lt;/p&gt;\n\n&lt;p&gt;&lt;code&gt;link_id&lt;/code&gt; should be the ID of the submission. In your case, &lt;code&gt;t3_o0pk5&lt;/code&gt;.&lt;/p&gt;\n\n&lt;p&gt;&lt;code&gt;r&lt;/code&gt; is the name of the subreddit, and is only needed if you don&amp;#39;t include the subreddit in the URL (see my comments on &lt;a href=\"http://www.reddit.com/r/redditdev/comments/nvlmb/does_anyone_have_an_example_of_an_apiflairlist/\"&gt;this post&lt;/a&gt; for the explanation).&lt;/p&gt;\n\n&lt;p&gt;&lt;code&gt;api_type&lt;/code&gt; is only needed if you want to receive json results. Appending &lt;code&gt;.json&lt;/code&gt; to the URL may accomplish the same thing, though I&amp;#39;ve found with &lt;code&gt;POST&lt;/code&gt; requests, that typically isn&amp;#39;t the case as often you&amp;#39;ll get back &lt;em&gt;jquery&lt;/em&gt; results.&lt;/p&gt;\n\n&lt;p&gt;If you can follow python check out my code here:\n&lt;a href=\"https://github.com/mellort/reddit_api/blob/master/reddit/objects.py#L254\"&gt;https://github.com/mellort/reddit_api/blob/master/reddit/objects.py#L254&lt;/a&gt;&lt;/p&gt;\n\n&lt;hr/&gt;\n\n&lt;p&gt;Edit: I forgot to mention, that the &lt;code&gt;children&lt;/code&gt; IDs may not always actually be children of the location where the &lt;code&gt;more&lt;/code&gt; object appears. Thus you have to manually reconstruct the comment tree.&lt;/p&gt;\n\n&lt;p&gt;Also, knowing that I had to manually reconstruct the tree, I figured I could just batch request all the &lt;code&gt;more&lt;/code&gt; IDs. Unfortunately that doesn&amp;#39;t work, as it&amp;#39;ll only return a partial result. You have to make one request for each &lt;code&gt;more&lt;/code&gt; object, which makes obtaining all the comments for a heavily-commented submission require numerous requests.&lt;/p&gt;\n&lt;/div&gt;",
                        "removal_reason": null,
                        "collapsed_reason": null,
                        "distinguished": null,
                        "associated_award": null,
                        "stickied": false,
                        "author_premium": false,
                        "can_gild": true,
                        "gildings": {},
                        "unrepliable_reason": null,
                        "author_flair_text_color": "dark",
                        "score_hidden": false,
                        "permalink": "/r/redditdev/comments/o1w7b/how_do_i_get_more_comments_in_json_format/c3dpt9i/",
                        "subreddit_type": "public",
                        "locked": false,
                        "report_reasons": null,
                        "created": 1325646819.0,
                        "author_flair_text": "PRAW Author",
                        "treatment_tags": [],
                        "link_id": "t3_o1w7b",
                        "subreddit_name_prefixed": "r/redditdev",
                        "controversiality": 0,
                        "depth": 0,
                        "author_flair_background_color": "",
                        "collapsed_because_crowd_control": null,
                        "mod_reports": [],
                        "num_reports": null,
                        "ups": 4
                    }
                },
                {
                    "kind": "t1",
                    "data": {
                        "subreddit_id": "t5_2qizd",
                        "approved_at_utc": null,
                        "author_is_blocked": false,
                        "comment_type": null,
                        "awarders": [],
                        "mod_reason_by": null,
                        "banned_by": null,
                        "author_flair_type": "text",
                        "total_awards_received": 0,
                        "subreddit": "redditdev",
                        "author_flair_template_id": null,
                        "likes": null,
                        "replies": {
                            "kind": "Listing",
                            "data": {
                                "after": null,
                                "dist": null,
                                "modhash": "cnfgw4ugmc6bb75362bc0967b9a7c422f366c35de7699bef2d",
                                "geo_filter": "",
                                "children": [
                                    {
                                        "kind": "t1",
                                        "data": {
                                            "subreddit_id": "t5_2qizd",
                                            "approved_at_utc": null,
                                            "author_is_blocked": false,
                                            "comment_type": null,
                                            "awarders": [],
                                            "mod_reason_by": null,
                                            "banned_by": null,
                                            "author_flair_type": "text",
                                            "total_awards_received": 0,
                                            "subreddit": "redditdev",
                                            "author_flair_template_id": null,
                                            "likes": null,
                                            "replies": {
                                                "kind": "Listing",
                                                "data": {
                                                    "after": null,
                                                    "dist": null,
                                                    "modhash": "cnfgw4ugmc6bb75362bc0967b9a7c422f366c35de7699bef2d",
                                                    "geo_filter": "",
                                                    "children": [
                                                        {
                                                            "kind": "t1",
                                                            "data": {
                                                                "subreddit_id": "t5_2qizd",
                                                                "approved_at_utc": null,
                                                                "author_is_blocked": false,
                                                                "comment_type": null,
                                                                "awarders": [],
                                                                "mod_reason_by": null,
                                                                "banned_by": null,
                                                                "author_flair_type": "text",
                                                                "total_awards_received": 0,
                                                                "subreddit": "redditdev",
                                                                "author_flair_template_id": null,
                                                                "likes": null,
                                                                "replies": {
                                                                    "kind": "Listing",
                                                                    "data": {
                                                                        "after": null,
                                                                        "dist": null,
                                                                        "modhash": "cnfgw4ugmc6bb75362bc0967b9a7c422f366c35de7699bef2d",
                                                                        "geo_filter": "",
                                                                        "children": [
                                                                            {
                                                                                "kind": "t1",
                                                                                "data": {
                                                                                    "subreddit_id": "t5_2qizd",
                                                                                    "approved_at_utc": null,
                                                                                    "author_is_blocked": false,
                                                                                    "comment_type": null,
                                                                                    "awarders": [],
                                                                                    "mod_reason_by": null,
                                                                                    "banned_by": null,
                                                                                    "author_flair_type": "text",
                                                                                    "total_awards_received": 0,
                                                                                    "subreddit": "redditdev",
                                                                                    "author_flair_template_id": null,
                                                                                    "likes": null,
                                                                                    "replies": {
                                                                                        "kind": "Listing",
                                                                                        "data": {
                                                                                            "after": null,
                                                                                            "dist": null,
                                                                                            "modhash": "cnfgw4ugmc6bb75362bc0967b9a7c422f366c35de7699bef2d",
                                                                                            "geo_filter": "",
                                                                                            "children": [
                                                                                                {
                                                                                                    "kind": "t1",
                                                                                                    "data": {
                                                                                                        "subreddit_id": "t5_2qizd",
                                                                                                        "approved_at_utc": null,
                                                                                                        "author_is_blocked": false,
                                                                                                        "comment_type": null,
                                                                                                        "awarders": [],
                                                                                                        "mod_reason_by": null,
                                                                                                        "banned_by": null,
                                                                                                        "author_flair_type": "text",
                                                                                                        "total_awards_received": 0,
                                                                                                        "subreddit": "redditdev",
                                                                                                        "author_flair_template_id": null,
                                                                                                        "distinguished": null,
                                                                                                        "likes": null,
                                                                                                        "replies": "",
                                                                                                        "user_reports": [],
                                                                                                        "saved": false,
                                                                                                        "id": "c3tr5h7",
                                                                                                        "banned_at_utc": null,
                                                                                                        "mod_reason_title": null,
                                                                                                        "gilded": 0,
                                                                                                        "archived": false,
                                                                                                        "collapsed_reason_code": null,
                                                                                                        "no_follow": true,
                                                                                                        "author": "musicOcean",
                                                                                                        "can_mod_post": false,
                                                                                                        "send_replies": true,
                                                                                                        "parent_id": "t1_c3dqqpg",
                                                                                                        "score": 1,
                                                                                                        "author_fullname": "t2_3pcp6",
                                                                                                        "removal_reason": null,
                                                                                                        "approved_by": null,
                                                                                                        "mod_note": null,
                                                                                                        "all_awardings": [],
                                                                                                        "body": "test post comment, up vote",
                                                                                                        "edited": false,
                                                                                                        "author_flair_css_class": null,
                                                                                                        "name": "t1_c3tr5h7",
                                                                                                        "is_submitter": false,
                                                                                                        "downs": 0,
                                                                                                        "author_flair_richtext": [],
                                                                                                        "author_patreon_flair": false,
                                                                                                        "body_html": "&lt;div class=\"md\"&gt;&lt;p&gt;test post comment, up vote&lt;/p&gt;\n&lt;/div&gt;",
                                                                                                        "gildings": {},
                                                                                                        "collapsed_reason": null,
                                                                                                        "link_id": "t3_o1w7b",
                                                                                                        "associated_award": null,
                                                                                                        "stickied": false,
                                                                                                        "author_premium": false,
                                                                                                        "can_gild": true,
                                                                                                        "top_awarded_type": null,
                                                                                                        "unrepliable_reason": null,
                                                                                                        "author_flair_text_color": null,
                                                                                                        "treatment_tags": [],
                                                                                                        "score_hidden": false,
                                                                                                        "permalink": "/r/redditdev/comments/o1w7b/how_do_i_get_more_comments_in_json_format/c3tr5h7/",
                                                                                                        "subreddit_type": "public",
                                                                                                        "locked": false,
                                                                                                        "report_reasons": null,
                                                                                                        "created": 1329902506.0,
                                                                                                        "author_flair_text": null,
                                                                                                        "collapsed": false,
                                                                                                        "created_utc": 1329902506.0,
                                                                                                        "subreddit_name_prefixed": "r/redditdev",
                                                                                                        "controversiality": 0,
                                                                                                        "depth": 4,
                                                                                                        "author_flair_background_color": null,
                                                                                                        "collapsed_because_crowd_control": null,
                                                                                                        "mod_reports": [],
                                                                                                        "num_reports": null,
                                                                                                        "ups": 1
                                                                                                    }
                                                                                                }
                                                                                            ],
                                                                                            "before": null
                                                                                        }
                                                                                    },
                                                                                    "user_reports": [],
                                                                                    "saved": false,
                                                                                    "id": "c3dqqpg",
                                                                                    "banned_at_utc": null,
                                                                                    "mod_reason_title": null,
                                                                                    "gilded": 0,
                                                                                    "archived": false,
                                                                                    "collapsed_reason_code": null,
                                                                                    "no_follow": true,
                                                                                    "author": "bboe",
                                                                                    "can_mod_post": false,
                                                                                    "send_replies": true,
                                                                                    "parent_id": "t1_c3dqlns",
                                                                                    "score": 3,
                                                                                    "author_fullname": "t2_3pz6e",
                                                                                    "removal_reason": null,
                                                                                    "approved_by": null,
                                                                                    "mod_note": null,
                                                                                    "all_awardings": [],
                                                                                    "collapsed": false,
                                                                                    "body": "That is exactly what the `api/morechildren` that I describe above does.",
                                                                                    "edited": false,
                                                                                    "top_awarded_type": null,
                                                                                    "author_flair_css_class": "",
                                                                                    "name": "t1_c3dqqpg",
                                                                                    "is_submitter": false,
                                                                                    "downs": 0,
                                                                                    "author_flair_richtext": [],
                                                                                    "author_patreon_flair": false,
                                                                                    "body_html": "&lt;div class=\"md\"&gt;&lt;p&gt;That is exactly what the &lt;code&gt;api/morechildren&lt;/code&gt; that I describe above does.&lt;/p&gt;\n&lt;/div&gt;",
                                                                                    "gildings": {},
                                                                                    "collapsed_reason": null,
                                                                                    "distinguished": null,
                                                                                    "associated_award": null,
                                                                                    "stickied": false,
                                                                                    "author_premium": false,
                                                                                    "can_gild": true,
                                                                                    "link_id": "t3_o1w7b",
                                                                                    "unrepliable_reason": null,
                                                                                    "author_flair_text_color": "dark",
                                                                                    "score_hidden": false,
                                                                                    "permalink": "/r/redditdev/comments/o1w7b/how_do_i_get_more_comments_in_json_format/c3dqqpg/",
                                                                                    "subreddit_type": "public",
                                                                                    "locked": false,
                                                                                    "report_reasons": null,
                                                                                    "created": 1325653617.0,
                                                                                    "author_flair_text": "PRAW Author",
                                                                                    "treatment_tags": [],
                                                                                    "created_utc": 1325653617.0,
                                                                                    "subreddit_name_prefixed": "r/redditdev",
                                                                                    "controversiality": 0,
                                                                                    "depth": 3,
                                                                                    "author_flair_background_color": "",
                                                                                    "collapsed_because_crowd_control": null,
                                                                                    "mod_reports": [],
                                                                                    "num_reports": null,
                                                                                    "ups": 3
                                                                                }
                                                                            }
                                                                        ],
                                                                        "before": null
                                                                    }
                                                                },
                                                                "user_reports": [],
                                                                "saved": false,
                                                                "id": "c3dqlns",
                                                                "banned_at_utc": null,
                                                                "mod_reason_title": null,
                                                                "gilded": 0,
                                                                "archived": false,
                                                                "collapsed_reason_code": null,
                                                                "no_follow": true,
                                                                "author": "fullouterjoin",
                                                                "can_mod_post": false,
                                                                "send_replies": true,
                                                                "parent_id": "t1_c3dqdb6",
                                                                "score": 1,
                                                                "author_fullname": "t2_406sj",
                                                                "removal_reason": null,
                                                                "approved_by": null,
                                                                "mod_note": null,
                                                                "all_awardings": [],
                                                                "body": "reddit is all borked right now, but I would reverse engineer the \"load more comments\" javascript that runs. It doesn't appear trivial. Otherwise look at the source and see if there is a way to finesse the comments out.",
                                                                "edited": false,
                                                                "top_awarded_type": null,
                                                                "downs": 0,
                                                                "author_flair_css_class": null,
                                                                "name": "t1_c3dqlns",
                                                                "is_submitter": false,
                                                                "collapsed": false,
                                                                "author_flair_richtext": [],
                                                                "author_patreon_flair": false,
                                                                "body_html": "&lt;div class=\"md\"&gt;&lt;p&gt;reddit is all borked right now, but I would reverse engineer the &amp;quot;load more comments&amp;quot; javascript that runs. It doesn&amp;#39;t appear trivial. Otherwise look at the source and see if there is a way to finesse the comments out.&lt;/p&gt;\n&lt;/div&gt;",
                                                                "gildings": {},
                                                                "collapsed_reason": null,
                                                                "distinguished": null,
                                                                "associated_award": null,
                                                                "stickied": false,
                                                                "author_premium": false,
                                                                "can_gild": true,
                                                                "link_id": "t3_o1w7b",
                                                                "unrepliable_reason": null,
                                                                "author_flair_text_color": null,
                                                                "score_hidden": false,
                                                                "permalink": "/r/redditdev/comments/o1w7b/how_do_i_get_more_comments_in_json_format/c3dqlns/",
                                                                "subreddit_type": "public",
                                                                "locked": false,
                                                                "report_reasons": null,
                                                                "created": 1325652520.0,
                                                                "author_flair_text": null,
                                                                "treatment_tags": [],
                                                                "created_utc": 1325652520.0,
                                                                "subreddit_name_prefixed": "r/redditdev",
                                                                "controversiality": 0,
                                                                "depth": 2,
                                                                "author_flair_background_color": null,
                                                                "collapsed_because_crowd_control": null,
                                                                "mod_reports": [],
                                                                "num_reports": null,
                                                                "ups": 1
                                                            }
                                                        }
                                                    ],
                                                    "before": null
                                                }
                                            },
                                            "user_reports": [],
                                            "saved": false,
                                            "id": "c3dqdb6",
                                            "banned_at_utc": null,
                                            "mod_reason_title": null,
                                            "gilded": 0,
                                            "archived": false,
                                            "collapsed_reason_code": null,
                                            "no_follow": true,
                                            "author": "hyperpowerr",
                                            "can_mod_post": false,
                                            "created_utc": 1325650722.0,
                                            "send_replies": true,
                                            "parent_id": "t1_c3dqbcn",
                                            "score": 2,
                                            "author_fullname": "t2_3r45h",
                                            "removal_reason": null,
                                            "approved_by": null,
                                            "mod_note": null,
                                            "all_awardings": [],
                                            "body": "I am able to get additional stories in a subreddit just fine using the after key. I'm having trouble getting additional comments in each story itself.",
                                            "edited": false,
                                            "top_awarded_type": null,
                                            "author_flair_css_class": null,
                                            "name": "t1_c3dqdb6",
                                            "is_submitter": true,
                                            "downs": 0,
                                            "author_flair_richtext": [],
                                            "author_patreon_flair": false,
                                            "body_html": "&lt;div class=\"md\"&gt;&lt;p&gt;I am able to get additional stories in a subreddit just fine using the after key. I&amp;#39;m having trouble getting additional comments in each story itself.&lt;/p&gt;\n&lt;/div&gt;",
                                            "gildings": {},
                                            "collapsed_reason": null,
                                            "distinguished": null,
                                            "associated_award": null,
                                            "stickied": false,
                                            "author_premium": false,
                                            "can_gild": true,
                                            "link_id": "t3_o1w7b",
                                            "unrepliable_reason": null,
                                            "author_flair_text_color": null,
                                            "score_hidden": false,
                                            "permalink": "/r/redditdev/comments/o1w7b/how_do_i_get_more_comments_in_json_format/c3dqdb6/",
                                            "subreddit_type": "public",
                                            "locked": false,
                                            "report_reasons": null,
                                            "created": 1325650722.0,
                                            "author_flair_text": null,
                                            "treatment_tags": [],
                                            "collapsed": false,
                                            "subreddit_name_prefixed": "r/redditdev",
                                            "controversiality": 0,
                                            "depth": 1,
                                            "author_flair_background_color": null,
                                            "collapsed_because_crowd_control": null,
                                            "mod_reports": [],
                                            "num_reports": null,
                                            "ups": 2
                                        }
                                    }
                                ],
                                "before": null
                            }
                        },
                        "user_reports": [],
                        "saved": false,
                        "id": "c3dqbcn",
                        "banned_at_utc": null,
                        "mod_reason_title": null,
                        "gilded": 0,
                        "archived": false,
                        "collapsed_reason_code": null,
                        "no_follow": true,
                        "author": "fullouterjoin",
                        "can_mod_post": false,
                        "created_utc": 1325650304.0,
                        "send_replies": true,
                        "parent_id": "t3_o1w7b",
                        "score": 2,
                        "author_fullname": "t2_406sj",
                        "approved_by": null,
                        "mod_note": null,
                        "all_awardings": [],
                        "collapsed": false,
                        "body": "when you load a page `/.json` do you see the `after` key? use that to request subsequent pages.\n\n\n    after: t3_nyhvz\n\nhttp://www.reddit.com/r/programming/?count=25&amp;amp;after=t3_nyhvz\n\nI wasn't even aware I was subscribed to this subreddit.",
                        "edited": false,
                        "top_awarded_type": null,
                        "author_flair_css_class": null,
                        "name": "t1_c3dqbcn",
                        "is_submitter": false,
                        "downs": 0,
                        "author_flair_richtext": [],
                        "author_patreon_flair": false,
                        "body_html": "&lt;div class=\"md\"&gt;&lt;p&gt;when you load a page &lt;code&gt;/.json&lt;/code&gt; do you see the &lt;code&gt;after&lt;/code&gt; key? use that to request subsequent pages.&lt;/p&gt;\n\n&lt;pre&gt;&lt;code&gt;after: t3_nyhvz\n&lt;/code&gt;&lt;/pre&gt;\n\n&lt;p&gt;&lt;a href=\"http://www.reddit.com/r/programming/?count=25&amp;amp;amp;after=t3_nyhvz\"&gt;http://www.reddit.com/r/programming/?count=25&amp;amp;amp;after=t3_nyhvz&lt;/a&gt;&lt;/p&gt;\n\n&lt;p&gt;I wasn&amp;#39;t even aware I was subscribed to this subreddit.&lt;/p&gt;\n&lt;/div&gt;",
                        "removal_reason": null,
                        "collapsed_reason": null,
                        "distinguished": null,
                        "associated_award": null,
                        "stickied": false,
                        "author_premium": false,
                        "can_gild": true,
                        "gildings": {},
                        "unrepliable_reason": null,
                        "author_flair_text_color": null,
                        "score_hidden": false,
                        "permalink": "/r/redditdev/comments/o1w7b/how_do_i_get_more_comments_in_json_format/c3dqbcn/",
                        "subreddit_type": "public",
                        "locked": false,
                        "report_reasons": null,
                        "created": 1325650304.0,
                        "author_flair_text": null,
                        "treatment_tags": [],
                        "link_id": "t3_o1w7b",
                        "subreddit_name_prefixed": "r/redditdev",
                        "controversiality": 0,
                        "depth": 0,
                        "author_flair_background_color": null,
                        "collapsed_because_crowd_control": null,
                        "mod_reports": [],
                        "num_reports": null,
                        "ups": 2
                    }
                },
                {
                    "kind": "t1",
                    "data": {
                        "subreddit_id": "t5_2qizd",
                        "approved_at_utc": null,
                        "author_is_blocked": false,
                        "comment_type": null,
                        "awarders": [],
                        "mod_reason_by": null,
                        "banned_by": null,
                        "author_flair_type": "text",
                        "total_awards_received": 0,
                        "subreddit": "redditdev",
                        "author_flair_template_id": null,
                        "likes": null,
                        "replies": "",
                        "user_reports": [],
                        "saved": false,
                        "id": "c3dy84n",
                        "banned_at_utc": null,
                        "mod_reason_title": null,
                        "gilded": 0,
                        "archived": false,
                        "collapsed_reason_code": null,
                        "no_follow": true,
                        "author": "shinagle",
                        "can_mod_post": false,
                        "created_utc": 1325713554.0,
                        "send_replies": true,
                        "parent_id": "t3_o1w7b",
                        "score": 1,
                        "author_fullname": "t2_4cnfr",
                        "approved_by": null,
                        "mod_note": null,
                        "all_awardings": [],
                        "collapsed": false,
                        "body": "\"Since you asked, \\\"How do I get more comments in JSON format?\\\", I decided to leave my response here in JSON. Just ask!\"",
                        "edited": false,
                        "top_awarded_type": null,
                        "author_flair_css_class": null,
                        "name": "t1_c3dy84n",
                        "is_submitter": false,
                        "downs": 0,
                        "author_flair_richtext": [],
                        "author_patreon_flair": false,
                        "body_html": "&lt;div class=\"md\"&gt;&lt;p&gt;&amp;quot;Since you asked, \\&amp;quot;How do I get more comments in JSON format?\\&amp;quot;, I decided to leave my response here in JSON. Just ask!&amp;quot;&lt;/p&gt;\n&lt;/div&gt;",
                        "removal_reason": null,
                        "collapsed_reason": null,
                        "distinguished": null,
                        "associated_award": null,
                        "stickied": false,
                        "author_premium": false,
                        "can_gild": true,
                        "gildings": {},
                        "unrepliable_reason": null,
                        "author_flair_text_color": null,
                        "score_hidden": false,
                        "permalink": "/r/redditdev/comments/o1w7b/how_do_i_get_more_comments_in_json_format/c3dy84n/",
                        "subreddit_type": "public",
                        "locked": false,
                        "report_reasons": null,
                        "created": 1325713554.0,
                        "author_flair_text": null,
                        "treatment_tags": [],
                        "link_id": "t3_o1w7b",
                        "subreddit_name_prefixed": "r/redditdev",
                        "controversiality": 0,
                        "depth": 0,
                        "author_flair_background_color": null,
                        "collapsed_because_crowd_control": null,
                        "mod_reports": [],
                        "num_reports": null,
                        "ups": 1
                    }
                }
            ],
            "before": null
        }
    }
]
